{
    "サンディスク株式会社": [
        "https://www.westerndigital.com/ja-jp",
        "https://www.sandisk-jp.com/cs/"
    ],
    "株式会社イデアファクトリー": [
        "https://ideafactory.jp",
        "https://idea-fact.ocnk.net"
    ],
    "フロンティア株式会社": [
        "https://readycrew.jp",
        "http://www.frontier-jp.com",
        "https://recruit.frontier-gr.jp",
        "https://frontier-gr.jp",
        "https://www.frontiersman.co.jp",
        "https://www.frtr.jp"
    ],
    "Zenken株式会社": [
        "https://www.linguage.jp",
        "https://recruit.zenken.co.jp",
        "https://www.zenken.co.jp"
    ],
    "ITGマーケティング株式会社": [
        "https://www.itgm.co.jp"
    ],
    "株式会社アドテック": [
        "https://adtec-jp.com",
        "http://www.adtc.co.jp",
        "https://www.adtec-web.co.jp",
        "https://www.adtec.co.jp",
        "https://www.adtec-inc.co.jp",
        "http://www.ad-tech.biz"
    ],
    "株式会社南日本情報処理センター": [
        "https://www.kk-mic.jp"
    ],
    "株式会社東北データーサービス": [],
    "スイスビットジャパン株式会社": [],
    "ヒカワ石油株式会社": [],
    "ギッシュジャパン株式会社": [
        "https://gish-japan.com"
    ],
    "システムインテリジェント株式会社": [
        "https://www.intelligent.co.jp"
    ],
    "電気システムズ株式会社": [
        "https://makudenki.co.jp",
        "https://www.osaki-systems.com",
        "https://www.osaki.co.jp/ja/index.html"
    ],
    "株式会社松電": [
        "https://www.matsuden.ltd",
        "https://matuden.ti-da.net",
        "https://ksds.co.jp",
        "https://matsuden-k.co.jp",
        "https://matsuden.net",
        "https://www.s-d-s.jp",
        "https://www.shodensha-inc.co.jp/ja/"
    ],
    "株式会社ラ・クラシン": [],
    "デジタルアーツ株式会社": [
        "https://jobs.daj.jp",
        "https://www.daj.jp"
    ],
    "株式会社日本パープル": [
        "https://www.mamoru-kun.com"
    ],
    "株式会社ディアイティ": [
        "https://www.dit.co.jp"
    ],
    "株式会社ポトスセミコンダクター": [],
    "イーディーコントライブ株式会社": [
        "http://www.no-copy.jp",
        "https://www.safety-disclosure.jp",
        "https://www.ed-contrive.co.jp"
    ],
    "ケージーエス株式会社": [
        "https://www.kgs-jpn.co.jp"
    ],
    "株式会社シマンテック": [],
    "株式会社MIYABI": [
        "http://www.kenkosupport.jp",
        "http://nafudaya.com",
        "https://miyabi-sasebo.co.jp",
        "https://www.sadano.co.jp",
        "https://miyabiinc.jp"
    ],
    "アールアイジャパン株式会社": [
        "http://www.rijapan.co.jp"
    ],
    "東芝メモリ株式会社": [
        "http://www.toshiba-personalstorage.net/newsite/index_j.htm"
    ],
    "アンフェノールジャパン株式会社": [
        "https://www.amphenol.co.jp"
    ],
    "株式会社センチュリー": [
        "http://www.censys.co.jp",
        "http://century-grp.co.jp",
        "https://www.century.co.jp",
        "https://www.century21japan.co.jp",
        "https://centurykogyo.com",
        "http://century-asai.co.jp"
    ],
    "株式会社Hamaru": [
        "https://oshigoe.com",
        "https://www.hamaru.co.jp"
    ],
    "サンワサプライ株式会社": [
        "https://www.sanwa.co.jp",
        "https://direct.sanwa.co.jp/top/CSfTop.jsp"
    ],
    "株式会社ミロク情報サービス": [
        "https://www.mjs.co.jp",
        "https://recruit.mjs.co.jp",
        "https://www.tribeck.jp"
    ],
    "サイエンスパーク株式会社": [
        "https://sciencepark.co.jp",
        "https://aismiley.co.jp/category_page/work-station/"
    ],
    "株式会社アスク": [
        "https://www.asq-fs.co.jp",
        "https://www.ask-corp.jp",
        "https://www.asc.co.jp/",
        "https://www.askk.co.jp",
        "http://ask2003.co.jp",
        "https://www.ask-gp.co.jp",
        "https://www.ask-wa.jp"
    ],
    "ハギワラソリューションズ株式会社": [
        "http://www.hagisol.co.jp",
        "https://www.hagisol.co.jp"
    ],
    "オムロンソーシアルソリューションズ株式会社": [],
    "株式会社HHO": [
        "https://www.7sgood.com",
        "https://hho2020.com"
    ],
    "株式会社アルファネット": [
        "https://www.ooda-security.com",
        "https://www.anet.co.jp",
        "https://www.alphanet-inc.jp",
        "https://www.alfanet.co.jp"
    ],
    "日本ビクター株式会社": [],
    "株式会社大塚商会": [
        "https://jinzai.otsuka-shokai.co.jp",
        "https://mypage.otsuka-shokai.co.jp",
        "https://webdirect.tanomail.com",
        "https://www.otsuka-shokai.co.jp"
    ],
    "株式会社ディー・オー・エス": [
        "https://recruit.dos-osaka.co.jp",
        "https://www.dos-system.co.jp",
        "https://www.dos-osaka.co.jp"
    ],
    "株式会社磁気研究所": [
        "https://www.magneticlaboratories.com",
        "https://www.mag-labo.com"
    ],
    "株式会社南信精機製作所": [
        "https://www.nanshinss.co.jp"
    ],
    "大崎テクノサービス株式会社": [],
    "株式会社協和産業": [
        "https://www.kyowa-ids.jp",
        "http://www.kyowa-s.com",
        "http://www.kyowasangyo.net",
        "https://kyowa-ids.jp",
        "https://www.kyowa-sangyo.jp",
        "http://www.kyowacopy.com",
        "https://www.kyowainet.co.jp"
    ],
    "Sky株式会社": [
        "https://www.skygroup.jp",
        "https://www.sky-recruit.jp"
    ],
    "ユニバーサルコンピューター株式会社": [],
    "東京ガス株式会社": [
        "https://www.tokyogas-es.co.jp",
        "https://www.tokyogas-com.co.jp",
        "https://www.tokyo-gas-dx.com",
        "https://www.tokyo-gas.co.jp/index.html"
    ],
    "株式会社東芝": [],
    "株式会社アルファネット所属": [],
    "株式会社エム・オー・エム・テクノロジー": [
        "https://www.momt.co.jp"
    ],
    "アイティアクセス株式会社": [
        "https://www.itaccess.co.jp"
    ],
    "株式会社Box": [
        "https://www.box.com",
        "https://www.boxsquare.jp"
    ],
    "アドビ株式会社": [],
    "アラクサラネットワークス株式会社": [],
    "日本エルゴノミクス株式会社": [
        "https://www.edikun.co.jp"
    ],
    "北大阪急行電鉄株式会社": [
        "https://www.kita-kyu.co.jp"
    ],
    "北斗徽章株式会社": [
        "https://hk-anniversary.com",
        "https://hokutokisyou.com"
    ],
    "株式会社プリンストン": [
        "https://www.princeton.co.jp"
    ],
    "クオリティソフト株式会社": [
        "https://www.qualitysoft.com"
    ],
    "エムコマース株式会社": [
        "https://www.m-commercekk.jp"
    ],
    "株式会社アチェンド": [
        "https://www.accendo.co.jp"
    ],
    "富士通株式会社": [
        "https://fujitsu.recruiting.jp.fujitsu.com",
        "https://fujitsu-career.my.salesforce-sites.com"
    ],
    "Ｓｋｙ株式会社": [],
    "株式会社日立ソリューションズ": [
        "https://www.hitachi-solutions-create.co.jp",
        "https://www.hitachi-solutions.co.jp",
        "https://www.hitachi-solutions-tech.co.jp"
    ],
    "株式会社リンクスインターナショナル": [
        "https://www.links.co.jp"
    ],
    "株式会社グリーンハウス": [
        "https://www.greenhouse.co.jp",
        "https://www.green-house.co.jp",
        "https://www.ghf.co.jp"
    ],
    "トランセンドジャパン株式会社": [],
    "マックス株式会社": [
        "https://www.jyukan-shop-max.com",
        "https://www.max-ltd.co.jp"
    ],
    "NTTコミュニケーションズ株式会社": [
        "https://www.ntt.com/index.html"
    ],
    "株式会社エネゲート": [
        "http://www.enegate.co.jp",
        "https://www.enegate.co.jp"
    ],
    "株式会社創朋": [
        "https://soho-unsou.com",
        "https://soho-jp.com"
    ],
    "多摩電子工業株式会社": [
        "https://tamadenco.co.jp"
    ],
    "アンサー株式会社": [
        "http://www.answers.co.jp",
        "https://www.a-answer.co.jp",
        "https://answerinc.jp"
    ],
    "株式会社富士通研究所": [],
    "BIPROGY株式会社": [
        "https://www.biprogy.com",
        "https://www.biprogy.com/sustainability/"
    ],
    "アスエイト・アドバイザリー株式会社": [
        "https://www.forensic-invest.com",
        "https://asueito.com"
    ],
    "株式会社ZenmuTech": [
        "https://zenmutech.com"
    ],
    "大崎プラテック株式会社": [
        "http://www.osaki-platech.co.jp"
    ],
    "株式会社ヒューマンセントリックス": [
        "https://www.humancentrix.com"
    ],
    "株式会社オーム電機": [
        "https://www.ohm-electric.co.jp"
    ],
    "株式会社JMC": [
        "https://www.jmc-rp.co.jp",
        "https://www.heartroid.jp",
        "https://www.jmc-edu.co.jp",
        "https://www.jmc-trp.com",
        "https://www.metal-casting.jp"
    ],
    "株式会社日本総代理店": [
        "https://www.gkjapan.jp",
        "https://heimplanet.store"
    ],
    "翼通商株式会社": [],
    "エムオーテックス株式会社": [],
    "株式会社アーキサイト": [],
    "岩手大崎電気株式会社": [],
    "株式会社JVCケンウッド": [],
    "株式会社バッファロー": [],
    "菱洋エレクトロ株式会社": [],
    "株式会社ゲームテック": [],
    "大崎データテック株式会社": [],
    "株式会社エル・アンド・エフ": [],
    "エレコム株式会社": [],
    "ハイテクインター株式会社": [],
    "株式会社石川コンピュータ・センター": [],
    "株式会社QES": [],
    "大崎電気工業株式会社": [],
    "ウイーズ・システムズ株式会社": [],
    "株式会社ソニー・コンピュータエンタテインメント": [],
    "株式会社ハンモック": [],
    "大崎エステート株式会社": [],
    "株式会社Candee": [],
    "株式会社QUICK": [],
    "株式会社オクトン": []
}